Workbook
Name Job_gross_margin_January_All_jobs: 'Report'!$B$16
Name Job_gross_margin_December_All_jobs: 'Report'!$B$17
Name Gross_margin_jobs_need_to_break_even: 'Report'!$B$18
Name Job_gross_margin_January_Maintenance_contracts: 'Report'!$B$42
Name Job_gross_margin_December_Maintenance_contracts: 'Report'!$B$43
Name Gross_margin_jobs_need_to_break_even_2: 'Report'!$B$44
Name Job_gross_margin_January_Installations: 'Report'!$B$78
Name Job_gross_margin_December_Installations: 'Report'!$B$79
Name Gross_margin_jobs_need_to_break_even_3: 'Report'!$B$80
Name Job_gross_margin_January_Call_outs_and_repairs: 'Report'!$B$104
Name Job_gross_margin_December_Call_outs_and_repairs: 'Report'!$B$105
Name Gross_margin_jobs_need_to_break_even_4: 'Report'!$B$106
Name Technician_time_charged_January: 'Report'!$B$107
Name Materials_charged_January: 'Report'!$B$108

Sheet Report
A1: Which jobs actually make money?
A2: Sample Electrical & Air Pty Ltd · SAMPLE DATA (invented) · The Fourth Sheet · Made with Python (openpyxl)
A3: Period: January 2026 · Data status: Jan 2026 locked (data retrieved 2pm, Tue 6 Oct 2026) · Generated 22 Oct 2026, 4:57pm
A5: In short: Jobs made a 41.9% gross margin in January: maintenance contracts the most (63.8%), installations the least (32.0%).
A6: Every job's gross margin: revenue less materials, subcontractors and technician time at $68 an hour (fully loaded: wages and all on-costs). Pick a type of job and every number, chart and note on the page follows it.
A8: From gross margin to profit
A9: January's jobs made $76,716 gross margin (41.9%). Technician time not charged to jobs took $22,372 and overheads $58,730, leaving ($4,386) profit before tax ((2.4%) of revenue). To cover overheads, jobs need a 44.2% gross margin on average. (Workings sheet: "From gross margin to profit".)
A11: Gross margin, not profit
A12: Gross margin is not profit. Job gross margin = revenue less materials, subcontractors and technician time charged to the job at $68 an hour (wages and all on-costs). Not included: technician time not charged to any job (travel, training, waiting), and overheads (office wages, marketing, vehicles, rent, insurance, IT, depreciation, interest). Profit is what's left after those. Wages include their on-costs: super (12%) and leave as it's earned. No payroll tax: wages are under Queensland's $1.3 million threshold.
A14: Type of job: All jobs
A15: Headline number | B15: Value | C15: Compared with
A16: Job gross margin, January · All jobs | B16: =Workings!B28 | C16: target 35.0%
A17: Job gross margin, December · All jobs | B17: =Workings!C37 | C17: target 35.0%
A18: Gross margin jobs need to break even | B18: =Workings!B53 | C18: covers overheads and time not charged (January)
A20: Job gross margin by type of job, January 2026
B21: Gross margin % | C21: Gross margin $
A22: Maintenance contracts | B22: =Workings!B63 | C22: =Workings!B62
A23: Installations | B23: =Workings!B72 | C23: =Workings!B71
A24: Call-outs and repairs | B24: =Workings!B81 | C24: =Workings!B80
A34: What it shows
A35: In January maintenance contracts made a 63.8% job gross margin, installations made a 32.0% job gross margin, call-outs and repairs made a 47.6% job gross margin (technician time at $68 an hour, wages and all on-costs). Jobs need 44.2% just to cover overheads.
A37: What you'd do about it
A38: Installations: 32.0% gross margin, 3.0 points under the 35.0% target: about $3,301 on $109,100 of revenue in January. It's below the 44.2% needed to cover overheads, too. Maintenance contracts: 63.8% gross margin, 28.8 points over the 35.0% target ($11,549 ahead on $40,100 in January).
A40: Type of job: Maintenance contracts
A41: Headline number | B41: Value | C41: Compared with
A42: Job gross margin, January · Maintenance contracts | B42: =Workings!B90 | C42: target 35.0%
A43: Job gross margin, December · Maintenance contracts | B43: =Workings!B99 | C43: target 35.0%
A44: Gross margin jobs need to break even | B44: =Workings!B115 | C44: covers overheads and time not charged (January)
A46: Job gross margin on each maintenance contract, January 2026
B47: Gross margin % | C47: Gross margin $
A48: Wynnum medical centre | B48: =Workings!B129 | C48: =Workings!B128
A49: Ashgrove aged care | B49: =Workings!B142 | C49: =Workings!B141
A50: Riverside Apartments (strata) | B50: =Workings!B155 | C50: =Workings!B154
A51: Newstead gym | B51: =Workings!B168 | C51: =Workings!B167
A52: Fortitude Valley hotel | B52: =Workings!B181 | C52: =Workings!B180
A53: Southbank cafe group | B53: =Workings!B194 | C53: =Workings!B193
A54: Chermside retail centre | B54: =Workings!B207 | C54: =Workings!B206
A55: Bulimba school | B55: =Workings!B220 | C55: =Workings!B219
A56: Milton office tower | B56: =Workings!B233 | C56: =Workings!B232
A57: West End brewery | B57: =Workings!B246 | C57: =Workings!B245
A58: Rocklea factory | B58: =Workings!B259 | C58: =Workings!B258
A59: Kangaroo Point townhouses | B59: =Workings!B272 | C59: =Workings!B271
A70: What it shows
A71: All 12 contracts made more than the 35.0% job gross margin target. The thinnest was Kangaroo Point townhouses at 62.9% job gross margin: 14.0 h of technician time on a $2,700 monthly fee.
A73: What you'd do about it
A74: The thinnest, Kangaroo Point townhouses: 62.9% gross margin, 27.9 points over the 35.0% target ($753 ahead on $2,700 in January). All maintenance contracts: 63.8% gross margin, 28.8 points over the 35.0% target ($11,549 ahead on $40,100 in January).
A76: Type of job: Installations
A77: Headline number | B77: Value | C77: Compared with
A78: Job gross margin, January · Installations | B78: =Workings!B281 | C78: target 35.0%
A79: Job gross margin, December · Installations | B79: =Workings!C290 | C79: target 35.0%
A80: Gross margin jobs need to break even | B80: =Workings!B306 | C80: covers overheads and time not charged (January)
A82: Job gross margin on each installation invoiced in January 2026
B83: Gross margin % | C83: Gross margin $
A84: Chermside shop data cabling | B84: =Workings!B320 | C84: =Workings!B319
A85: Wynnum office data cabling | B85: =Workings!B333 | C85: =Workings!B332
A86: Milton townhouses switchboard upgrade | B86: =Workings!B346 | C86: =Workings!B345
A87: West End factory switchboard upgrade | B87: =Workings!B359 | C87: =Workings!B358
A88: Mount Gravatt clinic solar and battery | B88: =Workings!B372 | C88: =Workings!B371
A96: What it shows
A97: 3 of the 5 installation jobs invoiced in January made less than the 35.0% job gross margin target. The Mount Gravatt clinic solar and battery made a 19.6% job gross margin: 110.0 h of technician time ($7,480) and $3,000 of subcontractors on a $30,200 job. Jobs need 44.2% gross margin just to cover overheads.
A99: What you'd do about it
A100: 3 installations under the 35.0% target, worth about $5,859 between them on $75,900 of revenue. The biggest gap, Mount Gravatt clinic solar and battery: 19.6% gross margin, 15.4 points under the 35.0% target: about $4,650 on $30,200 of revenue in January. It's below the 44.2% needed to cover overheads, too.
A102: Type of job: Call-outs and repairs
A103: Headline number | B103: Value | C103: Compared with
A104: Job gross margin, January · Call-outs and repairs | B104: =Workings!B381 | C104: target 35.0%
A105: Job gross margin, December · Call-outs and repairs | B105: =Workings!C390 | C105: target 35.0%
A106: Gross margin jobs need to break even | B106: =Workings!B406 | C106: covers overheads and time not charged (January)
A107: Technician time charged, January | B107: =Workings!B413 | C107: 69.8% of call-out revenue
A108: Materials charged, January | B108: =Workings!B429 | C108: $7,930 at cost, plus 30%
A110: Job gross margin on call-outs by length, January 2026
B111: Gross margin % | C111: Gross margin $
A112: 1-hour call-outs (7) | B112: =Workings!B444 | C112: =Workings!B443
A113: 1.5-hour call-outs (11) | B113: =Workings!B457 | C113: =Workings!B456
A114: 2-hour call-outs (8) | B114: =Workings!B470 | C114: =Workings!B469
A115: 2.5-hour call-outs (11) | B115: =Workings!B483 | C115: =Workings!B482
A116: 3-hour call-outs (21) | B116: =Workings!B496 | C116: =Workings!B495
A117: 4-hour call-outs (4) | B117: =Workings!B509 | C117: =Workings!B508
A126: What it shows
A127: 62 call-outs in January billed $23,797 of technician time and $10,309 of materials ($7,930 at cost plus 30%), and made a 47.6% job gross margin between them. Gross margins run from 40.7% to 50.8% by length: the hourly rate covers technician time comfortably, so the gross margin mostly moves with how much material goes on the van.
A129: What you'd do about it
A130: All call-outs: 47.6% gross margin, 12.6 points over the 35.0% target ($4,311 ahead on $34,106 in January).
A132: Every type of job at once
A133: Job gross margin by month: every month is on the Data sheet.

Sheet Workings
A1: How each number is worked out
A2: Sample Electrical & Air Pty Ltd · SAMPLE DATA (invented) · The Fourth Sheet · Made with Python (openpyxl)
A3: Period: January 2026 · Data status: Jan 2026 locked (data retrieved 2pm, Tue 6 Oct 2026) · Generated 22 Oct 2026, 4:57pm
A5: Trades: From gross margin to profit, January 2026
A6: Gross margin on the work − time not charged − overheads = profit before tax
B7: Jan 2026
A8: Gross margin on jobs | B8: 76716
A9: Technician wages and on-costs | B9: 72352
A10: Technician time charged to jobs (at cost) | B10: 49980
A11: Technician time not charged to jobs | B11: =B9-B10
A12: Gross profit (the P&L) | B12: =B8-B11
A13: Overheads (operating expenses, depreciation, interest) | B13: 58730
A14: Profit before tax (the P&L) | B14: =B12-B13
A15: Revenue | B15: 183306
A16: Gross margin on jobs, % | B16: =B8/B15
A17: Profit before tax, % of revenue | B17: =B14/B15
A18: Gross margin jobs need just to cover overheads and time not charged | B18: =(B11+B13)/B15
A19: Ties to the January 2026 P&L (locked). Wages include their on-costs: super (12%) and leave as it's earned. No payroll tax: wages are under Queensland's $1.3 million threshold.
A22: Trades, all lines: gross margin, January and December
A23: Revenue less direct cost, over revenue. Before overheads.
B24: Jan 26 | C24: Dec 25
A25: Revenue | B25: 183306 | C25: 150283
A26: Direct cost | B26: 106590 | C26: 84626
A27: Gross margin | B27: =B25-B26 | C27: =C25-C26
A28: Gross margin % | B28: =B27/B25 | C28: =C27/C25
A31: Trades, all lines: gross margin, January and December
A32: Revenue less direct cost, over revenue. Before overheads.
B33: Jan 26 | C33: Dec 25
A34: Revenue | B34: 183306 | C34: 150283
A35: Direct cost | B35: 106590 | C35: 84626
A36: Gross margin | B36: =B34-B35 | C36: =C34-C35
A37: Gross margin % | B37: =B36/B34 | C37: =C36/C34
A40: Trades: From gross margin to profit, January 2026
A41: Gross margin on the work − time not charged − overheads = profit before tax
B42: Jan 2026
A43: Gross margin on jobs | B43: 76716
A44: Technician wages and on-costs | B44: 72352
A45: Technician time charged to jobs (at cost) | B45: 49980
A46: Technician time not charged to jobs | B46: =B44-B45
A47: Gross profit (the P&L) | B47: =B43-B46
A48: Overheads (operating expenses, depreciation, interest) | B48: 58730
A49: Profit before tax (the P&L) | B49: =B47-B48
A50: Revenue | B50: 183306
A51: Gross margin on jobs, % | B51: =B43/B50
A52: Profit before tax, % of revenue | B52: =B49/B50
A53: Gross margin jobs need just to cover overheads and time not charged | B53: =(B46+B48)/B50
A54: Ties to the January 2026 P&L (locked). Wages include their on-costs: super (12%) and leave as it's earned. No payroll tax: wages are under Queensland's $1.3 million threshold.
A57: Maintenance contracts, January
A58: Revenue less direct cost (materials, subcontractors, technician time at cost)
B59: Jan 2026
A60: Revenue | B60: 40100
A61: Direct cost | B61: 14516
A62: Gross margin | B62: =B60-B61
A63: Gross margin % | B63: =B62/B60
A66: Installations, January
A67: Revenue less direct cost (materials, subcontractors, technician time at cost)
B68: Jan 2026
A69: Revenue | B69: 109100
A70: Direct cost | B70: 74216
A71: Gross margin | B71: =B69-B70
A72: Gross margin % | B72: =B71/B69
A75: Call-outs and repairs, January
A76: Revenue less direct cost (materials, subcontractors, technician time at cost)
B77: Jan 2026
A78: Revenue | B78: 34106
A79: Direct cost | B79: 17858
A80: Gross margin | B80: =B78-B79
A81: Gross margin % | B81: =B80/B78
A84: Trades, Maintenance contracts: gross margin, January and December
A85: Revenue less direct cost, over revenue. Before overheads.
B86: Jan 26 | C86: Dec 25
A87: Revenue | B87: 40100 | C87: 40100
A88: Direct cost | B88: 14516 | C88: 14516
A89: Gross margin | B89: =B87-B88 | C89: =C87-C88
A90: Gross margin % | B90: =B89/B87 | C90: =C89/C87
A93: Trades, Maintenance contracts: gross margin, January and December
A94: Revenue less direct cost, over revenue. Before overheads.
B95: Jan 26 | C95: Dec 25
A96: Revenue | B96: 40100 | C96: 40100
A97: Direct cost | B97: 14516 | C97: 14516
A98: Gross margin | B98: =B96-B97 | C98: =C96-C97
A99: Gross margin % | B99: =B98/B96 | C99: =C98/C96
A102: Trades: From gross margin to profit, January 2026
A103: Gross margin on the work − time not charged − overheads = profit before tax
B104: Jan 2026
A105: Gross margin on jobs | B105: 76716
A106: Technician wages and on-costs | B106: 72352
A107: Technician time charged to jobs (at cost) | B107: 49980
A108: Technician time not charged to jobs | B108: =B106-B107
A109: Gross profit (the P&L) | B109: =B105-B108
A110: Overheads (operating expenses, depreciation, interest) | B110: 58730
A111: Profit before tax (the P&L) | B111: =B109-B110
A112: Revenue | B112: 183306
A113: Gross margin on jobs, % | B113: =B105/B112
A114: Profit before tax, % of revenue | B114: =B111/B112
A115: Gross margin jobs need just to cover overheads and time not charged | B115: =(B108+B110)/B112
A116: Ties to the January 2026 P&L (locked). Wages include their on-costs: super (12%) and leave as it's earned. No payroll tax: wages are under Queensland's $1.3 million threshold.
A119: Wynnum medical centre
A120: Job gross margin ÷ revenue for this job (before overheads)
B121: This job
...

Sheet Chart lines
A1: Points for the target and break-even lines drawn on the charts (hidden sheet; edit the values on the chart's own sheet).
A3: Report: Job gross margin by type of job, January 2026: Target 35.0%
B4: 0.35 | C4: 0
B5: 0.35 | C5: 1
A7: Report: Job gross margin by type of job, January 2026: Break-even 44.2%
B8: 0.442 | C8: 0
B9: 0.442 | C9: 1
A11: Report: Job gross margin on each maintenance contract, January 2026: Target 35.0%
B12: 0.35 | C12: 0
B13: 0.35 | C13: 1
A15: Report: Job gross margin on each maintenance contract, January 2026: Break-even 44.2%
B16: 0.442 | C16: 0
B17: 0.442 | C17: 1
A19: Report: Job gross margin on each installation invoiced in January 2026: Target 35.0%
B20: 0.35 | C20: 0
B21: 0.35 | C21: 1
A23: Report: Job gross margin on each installation invoiced in January 2026: Break-even 44.2%
B24: 0.442 | C24: 0
B25: 0.442 | C25: 1
A27: Report: Job gross margin on call-outs by length, January 2026: Target 35.0%
B28: 0.35 | C28: 0
B29: 0.35 | C29: 1
A31: Report: Job gross margin on call-outs by length, January 2026: Break-even 44.2%
B32: 0.442 | C32: 0
B33: 0.442 | C33: 1

Sheet Data
A1: Data
A2: Sample Electrical & Air Pty Ltd · SAMPLE DATA (invented) · The Fourth Sheet · Made with Python (openpyxl)
A3: Period: January 2026 · Data status: Jan 2026 locked (data retrieved 2pm, Tue 6 Oct 2026) · Generated 22 Oct 2026, 4:57pm
A5: Line | B5: Month | C5: Status | D5: Revenue | E5: Direct cost | F5: Gross margin | G5: Gross margin %
A6: All | B6: Oct 24 | C6: Locked | D6: 191014 | E6: 114334 | F6: =D6-E6 | G6: =IF(D6=0,"",F6/D6)
A7: All | B7: Nov 24 | C7: Locked | D7: 200124 | E7: 113016 | F7: =D7-E7 | G7: =IF(D7=0,"",F7/D7)
A8: All | B8: Dec 24 | C8: Locked | D8: 159406 | E8: 85316 | F8: =D8-E8 | G8: =IF(D8=0,"",F8/D8)
A9: All | B9: Jan 25 | C9: Locked | D9: 156794 | E9: 80742 | F9: =D9-E9 | G9: =IF(D9=0,"",F9/D9)
A10: All | B10: Feb 25 | C10: Locked | D10: 179190 | E10: 102348 | F10: =D10-E10 | G10: =IF(D10=0,"",F10/D10)
A11: All | B11: Mar 25 | C11: Locked | D11: 150465 | E11: 85752 | F11: =D11-E11 | G11: =IF(D11=0,"",F11/D11)
A12: All | B12: Apr 25 | C12: Locked | D12: 138865 | E12: 76808 | F12: =D12-E12 | G12: =IF(D12=0,"",F12/D12)
A13: All | B13: May 25 | C13: Locked | D13: 144649 | E13: 83700 | F13: =D13-E13 | G13: =IF(D13=0,"",F13/D13)
A14: All | B14: Jun 25 | C14: Locked | D14: 183265 | E14: 97584 | F14: =D14-E14 | G14: =IF(D14=0,"",F14/D14)
A15: All | B15: Jul 25 | C15: Locked | D15: 208588 | E15: 120326 | F15: =D15-E15 | G15: =IF(D15=0,"",F15/D15)
A16: All | B16: Aug 25 | C16: Locked | D16: 155118 | E16: 78258 | F16: =D16-E16 | G16: =IF(D16=0,"",F16/D16)
A17: All | B17: Sep 25 | C17: Locked | D17: 143077 | E17: 80054 | F17: =D17-E17 | G17: =IF(D17=0,"",F17/D17)
... A69: Call-outs and repairs | B69: Jan 26 | C69: Locked | D69: 34106 | E69: 17858 | F69: =D69-E69 | G69: =IF(D69=0,"",F69/D69)
